{
  "_cloudtap": true,
  "version": "0.1.53",
  "traces": [
    {
      "timestamp": "20260511_103658",
      "files": [
        "2026-05-11/trace_103658.jsonl",
        "2026-05-11/trace_103658.log",
        "2026-05-11/trace_103658.html"
      ],
      "created_at": "2026-05-11T02:36:58.563297+00:00"
    },
    {
      "timestamp": "20260511_103658",
      "files": [
        "2026-05-11/trace_103658.jsonl",
        "2026-05-11/trace_103658.log",
        "2026-05-11/trace_103658.html"
      ],
      "created_at": "2026-05-11T02:37:23.665865+00:00"
    },
    {
      "timestamp": "20260511_103747",
      "files": [
        "2026-05-11/trace_103747.jsonl",
        "2026-05-11/trace_103747.log",
        "2026-05-11/trace_103747.html"
      ],
      "created_at": "2026-05-11T02:38:39.367231+00:00"
    },
    {
      "timestamp": "20260511_103959",
      "files": [
        "2026-05-11/trace_103959.jsonl",
        "2026-05-11/trace_103959.log",
        "2026-05-11/trace_103959.html"
      ],
      "created_at": "2026-05-11T02:41:15.348612+00:00"
    }
  ]
}
